{
	"mi":{
		"it":"Io/mi/me (1a persona singolare)"
	},
	"ti":{
		"it":"tu/te/ti (2a persona singolare)"
	},
	"si":{
		"it":"lui/lei/esso/lo/la/le (3a persona singolare)"
	},

	"a":{
		"it":"e",
		"es":"y"
	},
	"u":{
		"it":"o, oppure",
		"es":"o"
	},
	"i":{
		"var":"u",
		"tags":["NEC"]
	},
	"burger":{
		"it":"burger, hamburger",
		"es":"hamburguesa",
		"em":"🍔"
	},
	"taber":{
		"it":"mangiare"
	},
	"taberu":{
		"it":"bocca",
		"es":"boca"
	},
	"taberu ":{
		"var":"taber",
		"tags":["RA"]
	},
	"fikir":{
		"it":"pensare, credere",
		"es":"pensar, creer"
	},
	"fikr":{
		"var":"fikir"
	},
	"fikiru":{
		"it":"cervello",
		"es":"cerebro",
		"em":"🧠"
	},
	"yao":{
		"it":"amare, apprezzare",
		"es":"amar, gustar"
	},
	"yau":{
		"it":"cuore",
		"es":"corazón"
	},
	"wawau":{
		"it":"ridere, risata",
		"es":"reír, risa"
	},
	"ne":{
		"it":"no, non"
	},
	"iko":{
		"it":"grande, largo, molto",
		"es":"gran"
	},
	"niko":{
		"it":"piccolo",
		"es":"pequeño"
	},

	"drinken":"(UNC) to drink (getting replaced by taber)",
	"zai":{
		"it":"in, dentro a, durante, "
	},

	"c'to":{
		"it":"ora, adesso",
		"es":"ahora"
	},

	"slapen":{
		"it":"dormire",
		"es":"dormir"
	},
	"slapenu":{
		"it":"letto"
	},
	"baza":{
		"it":"ape"
	},
	
	"slovo":{
		"it":"parola",
		"es":"palabra"
	},
	"solvo":{
		"var":"slovo"
	},

	"milao":{
		"it":"parlare, dire",
		"es":"hablar, dir"
	},
	"milau":{
		"it":"lingua",
		"es":"idioma"
	},
	"milava":{
		"it":"cosa detta, discorso, frase"
	},
	"mita":{
		"it":"che, il/la quale, pronome relativo e interrogativo, e anche congiunzione per domande"
	},
	"eta":{
		"it":"questo, questo qui, il/la"
	},
	"yabloko":{
		"it":"mela"
	},
	
	"voda":{
		"it":"acqua",
		"es":"agua"
	},
	"bazavoda":{
		"it":"miele",
		"es":"miel"
	},
	"casa":{
		"it":"casa",
		"es":"casa"
	},
	"kali":{
		"it":"bello, buono",
		"es":"hermoso, lindo"
	},

	"kalidyau":{
		"it":"buongiorno"
	},

	"kalymorno":{
		"it":"buona mattina"
	},
	"kalynoide":{
		"it":"buonanotte"
	},
	"dobro":{
		"it":"buono, ok",
		"es":"bueno, ok"
	},
	"bono":{
		"var":"dobro"
	},
	"tre":{
		"it":"molto",
		"es":"muy"
	},
	"morno":{
		"it":"mattino"
	},
	"dyau":{
		"it":"giorno",
		"es":"día"
	},
	"salo":{
		"it":"ciao",
		"es":"hola"
	},
	"etadyau":{
		"it":"oggi",
		"es":"hoy"
	},
	"weda":{
		"it":"ciao (per andarsene)",
		"es":"adiós"
	},
	"weida":{
		"var":"weda"
	},
	"adios":{
		"var":"weda"
	},
	"ni":{
		"it":"noi/ne/ci (1a pers. pl.)",
		"es":"nosotros (1a pers. pl.)"
	},

	"vi":{
		"it":"voi/ve/vi (2a pers. pl.)",
		"es":"vosotros (2a pers. pl.)"
	},



	"uwa":{
		"it":"terra, terreno, pianeta terra",
		"es":"tierra"
	},
	"hawa":{
		"it":"cielo",
		"es":"ciel"
	},
	"mujina":{
		"it":"persona"
	},

	"omo":"(UNC) person, human",
	"plus":{
		"it":"più, di più",
		"es":"más"
	},
	
	"xia":{
		"it":"tempo",
		"es":"tiempo"
	},



	"var":{
		"it":"precedente, prima di, indica tempo passato"
	},

	"varxia":{
		"it":"prima (nel tempo)"
	},
	
	"xukra":{
		"it":"grazie",
		"es":"gracias"
	},
	"noide":{
		"it":"notte",
		"es":"noche"
	},
	"noyde":{
		"var": "noite"
	},
	"nukta":{
		"var": "noite"
	},
	"kiel":{
		"it":"perché?",
		"es":"porque?"
	},
	"ogar":{
		"it":"da, da dove, origine (ablativo)",
		"es":"de donde"
	},
	"oni":{
		"it":"tutto, tutti",
		"es":"todos"
	},
	"omni":{
		"var":"oni"
	},
	"slovolisto":{
		"it":"dizionario",
		"es":"diccionario"
	},
	
	"diau":{
		"var":"dyau"
	},
	
	"us":{
		"it":"usare, fare uso di"
	},

	"glossa":{
		"var":"milau"
	},
	"sia":{
		"it":"essi/esse/loro (3a pers.pl.)"
	},
	"sie":{
		"var":"sia"
	},
	
	"slepen":{
		"var":"slapen"
	},
	"estas":{
		"var":"es"
	},
	"estan":{
		"var":"es"
	},
	"estar":{
		"var":"es"
	},
	"es":{
		"it":"essere (copula)"
	},
	
	"un":{
		"it":"uno (1), un, una"
	},
	"dua":{
		"it":"due (2)",
		"es":"dos (2)"
	},
	"du":{
		"var":"dua"
	},
	"tri":{
		"it":"tre (3)"
	},
	"est":{
		"var":"es",
		"tags":["NEC"]
	},
	
	"muxi":{
		"it":"insetto"
	},
	"omni xianzai":{
		"var":"onxia"
	},
	"onxia":{
		"it":"sempre",
		"es":"siempre"
	},
	"leul":{
		"it":"lento",
		"es":"lento"
	},
	"leule":{
		"it":"lentamente, piano",
		"es":"despacio"
	},

	"spidi":{
		"it":"veloce, rapido"
	},

	"spide":{
		"it":"velocemente"
	},

	"ruka":"hand (UNC) plural is unclear...",
	"tori":{
		"it":"uccello",
		"es":"pájaro",
		"em":"🐦",
		"tags":["GB"]
	},
	"koku":{
		"it":"re",
		"es":"rey"
	},
	"pisat":{
		"it":"scrivere",
		"es":"escrivir"
	},
	"pisatu":{
		"it":"matita",
		"es":"lapis"
	},
	"pisatva":{
		"it":"documento, scrittura, frase scritta",
		"es":"documento, escritura"
	},
	"maar":{
		"it":"ma, invece",
		"es":"pero"
	},
	
	"kan":{
		"it":"potere (verbo)",
		"es":"poder"
	},

	"kann":{
		"var":"kan"
	},

	"kannes":{
		"var":"kan es"
	},
	
	"scio":{
		"var":"jixi"
	},
	
	"nescio":{
		"var":"nejixi"
	},

	"nejixi":{
		"it":"non sapere, ignorare",
		"es":"ne saber"
	},

	"stento":{
		"it":"capire, comprendere",
		"es":"entender"
	},


	"comprend":{
		"var":"stento"
	},
	

	"wo":{
		"var":"mi",
		"tags":["AS"]
	},
	"wollen":{
		"it":"volere",
		"es":"voler"
	},
	"suman":{
		"it":"scusa",
		"es":"lo siento"
	},
	"we":{
		"var":"wollen",
		"tags":["RA"]
	},
	"sir":{
		"it":"successivo, prossimo, indica il futuro"
	},
	
	"lawa":{
		"it":"vecchio",
		"es":"viejo",
		"tags":["GB"]
	},
	"ober":{
		"var":"ogar"
	},
	"oinko":{
		"it":"maiale"
	},
	"mumu":{
		"it":"mucca",
		"es":"vaca",
		"em":"🐄"
	},
	"mumuvoda":{
		"it":"latte",
		"es":"leche",
		"em":"🥛"
	},
	"treda":{
		"it":"assolutamente sì"
	},
	"da":{
		"it":"sì"
	},


	"gusta":{
		"var":"yao"
	},
	"yappe":{
		"it":"cane"
	},
	"buau":{
		"var":"yappe",
		"tags":["AS","GB"]
	},
	"ikoyappe":{
		"it":"lupo",
		"es":"lobo",
		"tags":["RA"]
	},
	
	"myau":{
		"var":"mau",
		"tags":["AS","GB"]
	},
	"mau":{
		"it":"gatto",
		"es":"gato"
	},

	"maci":{
		"it":"pesce"
	},
	"nar":{
		"var":"var",
		"tags":["RA"]
	},
	"anki":{
		"it":"anche, pure",
		"es":"también"
	},
	"dobro":{
		"it":"buono, ok",
		"es":"bueno, ok"
	},
	"ok":{
		"it":"ok",
		"es":"ok"
	},
	"kak":{
		"it":"particella interrogativa per domande sì/no"
	},
	
	
	
	"dan":{
		"it":"dare, donare, fornire",
		"es":"dar"
	},
	"mak":{
		"it":"creare, costruire, produrre, fare (anche come causativo 'far fare')",
		"es":"crear, far, hacer"
	},
	"xiwu":{
		"it":"cibo"
	},
	"epo":{
		"var":"xukra"
	},
	"agori":{
		"it":"amico",
		"es":"amigo"
	},
	
	"myo":{
		"it":"vedere, provare a, cercare",
		"es":"ver, intentar de, buscar"
	},

	"myu":{
		"it":"occhio",
		"es":"ojo"
	},
	
	"idu":{
		"it":"andare, andarsene, ausiliario per futuro prossimo",
		"es":"ir, auxiliar por futuro proximo"
	},

	"xim":{
		"it":"morire, uccidere",
		"es":"morir, matar"
	},
	"xim":{
		"var":"ximu",
		"tags":["RA"]
	},
	"ximu":{
		"it":"morte",
		"es":"muerte"
	},
	"ximi":{
		"it":"morto",
		"es":"muerto"
	},

	"jixi":{
		"it":"sapere, conoscere",
		"es":"saber, conocer"
	},
	"forgo":{
		"it":"dimenticare",
		"es":"olvidar"
	},
	"jiximak":{
		"it":"imparare, insegnare",
		"es":"aprender, enseñar"
	},
	"mito":{
		"it":"chiedere, domandare",
		"es":"preguntar"
	},
	"mita":{
		"it":"domanda",
		"es":"pregunta"
	},
	"vot":{
		"it":"qui",
		"es":"aqui"
	},
	"voti":{
		"it":"vicino",
		"es":"cercano"
	},
	"sole":"(UNC) only (adverb)",
	"nevot":{
		"it":"là"
	},

	"nevoti":{
		"it":"lontano",
		"es":"lejano"
	},
	"fampeok":{
		"it":"confuso, confondibile",
		"es":"confus, confundible"
	},
	
	"mafu":{
		"var":"suman",
		"tags":["AS"]
	},
	"emotiu":{
		"it":"emozione",
		"es":"emoción"
	},
	"keyi":{
		"var":"kan",
		"tags":["AS"]
	},
	"ei":{
		"var":"un",
		"tags":["AS"]
	},
	"nuyen":{
		"it":"donna",
		"es":"mujer"
	},
	"nu'omo":"(AS) woman",
	"wanji":{
		"var":"nejixi",
		"tags":["AS"]
	},
	"aki":{
		"var":"vot",
		"tags":["RA","AS"]
	},
	"asoko":{
		"var":"nevot",
		"tags":["AS"]
	},
	"debe":{
		"var":"suldo"

	},
	"maru":{
		"it":"cerchio",
		"es":"circulo"
	},
	"semia":{
		"it":"famiglia",
		"es":"familia"
	},
	"aila":{
		"it":"fuoco, bruciare, dare fuoco",
		"es":"fuego, arder",
		"em":"🔥"
	},
	"arbo":{
		"it":"albero",
		"es":"árbol",
		"em":"🌳"
	},
	"pona":{
		"var":"yao",
		"tags":["AS"]
	},
	"ar":{
		"it":"aria",
		"es":"aire"
	},
	"gadu":{
		"it":"torta",
		"es":"pastel, tarta"
	},
	

	
	"ai":{
		"var":"yao",
		"tags":["RA","AS"]
	},
	
	"trexia":{
		"it":"spesso",
		"es":"a menudo"
	},
	"utraxia":{
		"it":"ancora, un'altra volta, di nuovo",
		"es":"de nuevo"
	},
	
	
	"suldo":{
		"it":"dovere, aver bisogno di",
		"es":"deber, necesitar"
	},
	"telos":{
		"it":"alcuni, qualche di",
		"es":"algunos"
	},
	"teloscaso":{
		"it":"in ogni caso",
		"es":"en cualquier caso"
	},
	"caso":{
		"it":"caso",
		"es":"caso"
	}
}